microssim/__init__.py
microssim/conftest.py
microssim/micro_ms3im.py
microssim/micro_ssim.py
microssim/image_processing/__init__.py
microssim/image_processing/background.py
microssim/image_processing/care_normalization.py
microssim/image_processing/linearize.py
microssim/image_processing/micro_ssim_normalization.py
microssim/ri_factor/__init__.py
microssim/ri_factor/mse_ri_factor.py
microssim/ri_factor/ri_factor.py
microssim/ssim/__init__.py
microssim/ssim/ssim_utils.py
microssim-0.0.3.dist-info/METADATA
microssim-0.0.3.dist-info/WHEEL
microssim-0.0.3.dist-info/licenses/LICENSE
microssim-0.0.3.dist-info/RECORD
