Metadata-Version: 2.4
Name: microssim
Version: 0.0.3
Summary: Improved structural similarity metrics for comparing microscopy data.
Project-URL: homepage, https://github.com/juglab/MicroSSIM
Project-URL: repository, https://github.com/juglab/MicroSSIM
Author: Ashesh, Joran Deschamps, Florian Jug
License: BSD-3-Clause
License-File: LICENSE
Classifier: Development Status :: 3 - Alpha
Classifier: License :: OSI Approved :: BSD License
Classifier: Programming Language :: Python :: 3
Classifier: Programming Language :: Python :: 3.9
Classifier: Programming Language :: Python :: 3.10
Classifier: Programming Language :: Python :: 3.11
Classifier: Programming Language :: Python :: 3.12
Classifier: Typing :: Typed
Requires-Python: >=3.11
Requires-Dist: numpy<3.0.0,>=1.21
Requires-Dist: scikit-image<=0.26.0
Requires-Dist: scipy<=1.17.0
Requires-Dist: torch<=2.9.1,>=2.5
Requires-Dist: torchmetrics<=1.8.2
Requires-Dist: tqdm<=4.67.1
Provides-Extra: dev
Requires-Dist: pre-commit; extra == 'dev'
Requires-Dist: pytest; extra == 'dev'
Requires-Dist: pytest-cov; extra == 'dev'
Requires-Dist: sybil; extra == 'dev'
Provides-Extra: examples
Requires-Dist: jupyter; extra == 'examples'
Requires-Dist: matplotlib; extra == 'examples'
Requires-Dist: pooch; extra == 'examples'
Requires-Dist: seaborn; extra == 'examples'
Requires-Dist: tifffile; extra == 'examples'
